MANIFEST.in
setup.py
docs/Usage.rst
docs/images/__getitem__.svg
docs/images/__init__.svg
docs/images/__setitem__.svg
docs/images/append_col-1.svg
docs/images/append_col-2.svg
docs/images/append_cols-1.svg
docs/images/append_cols-2.svg
docs/images/append_row-1.svg
docs/images/append_row-2.svg
docs/images/append_rows-1.svg
docs/images/append_rows-2.svg
docs/images/col.svg
docs/images/cols.svg
docs/images/crop.svg
docs/images/fliplr.svg
docs/images/flipud.svg
docs/images/insert_col-1.svg
docs/images/insert_col-2.svg
docs/images/insert_cols-1.svg
docs/images/insert_cols-2.svg
docs/images/insert_row-1.svg
docs/images/insert_row-2.svg
docs/images/insert_rows-1.svg
docs/images/insert_rows-2.svg
docs/images/prepend_col-1.svg
docs/images/prepend_col-2.svg
docs/images/prepend_cols-1.svg
docs/images/prepend_cols-2.svg
docs/images/prepend_row-1.svg
docs/images/prepend_row-2.svg
docs/images/prepend_rows-1.svg
docs/images/prepend_rows-2.svg
docs/images/reindex_cols.svg
docs/images/reindex_rows.svg
docs/images/rename_cols.svg
docs/images/repl_col-1.svg
docs/images/repl_col-2.svg
docs/images/repl_cols.svg
docs/images/repl_row-1.svg
docs/images/repl_row-2.svg
docs/images/repl_rows.svg
docs/images/rmcol.svg
docs/images/rmcols.svg
docs/images/rmrow.svg
docs/images/rmrows.svg
docs/images/row.svg
docs/images/rows.svg
docs/images/subtb.svg
docs/images/swapcol.svg
docs/images/swaprow.svg
docs/images/transpose.svg
qtable/__init__.py
qtable/engine.py
qtable/locs.py
qtable/ndarr.py
qtable/qtable.py
qtable/utils.py
qtable.egg-info/PKG-INFO
qtable.egg-info/SOURCES.txt
qtable.egg-info/dependency_links.txt
qtable.egg-info/top_level.txt