Metadata-Version: 1.1
Name: qtable
Version: 0.7
Summary: handle,.in progressing..,APIs
Home-page: https://github.com/ihgazni2/qtable
Author: dapeli
Author-email: terryinzaghi@163.com
License: MIT
Platform: UNKNOWN
Classifier: Environment :: Console
Classifier: Environment :: Web Environment
Classifier: Intended Audience :: End Users/Desktop
Classifier: Intended Audience :: Developers
Classifier: Intended Audience :: System Administrators
Classifier: Programming Language :: Python
